et_micc/__init__.py
et_micc/cli_micc.py
et_micc/db.py
et_micc/expand.py
et_micc/logger.py
et_micc/micc.json
et_micc/project.py
et_micc/static_vars.py
et_micc/templates/app-simple/{{cookiecutter.project_name}}/tests/test_{{cookiecutter.cli_app_name}}.{{cookiecutter.py}}
et_micc/templates/app-simple/{{cookiecutter.project_name}}/{{cookiecutter.package_name}}/{{cookiecutter.cli_app_name}}.{{cookiecutter.py}}
et_micc/templates/app-sub-commands/{{cookiecutter.project_name}}/tests/test_{{cookiecutter.cli_app_name}}.{{cookiecutter.py}}
et_micc/templates/app-sub-commands/{{cookiecutter.project_name}}/{{cookiecutter.package_name}}/{{cookiecutter.cli_app_name}}.{{cookiecutter.py}}
et_micc/templates/module-cpp/{{cookiecutter.project_name}}/tests/test_cpp_{{cookiecutter.module_name}}.{{cookiecutter.py}}
et_micc/templates/module-cpp/{{cookiecutter.project_name}}/{{cookiecutter.package_name}}/cpp_{{cookiecutter.module_name}}/CMakeLists.txt
et_micc/templates/module-cpp/{{cookiecutter.project_name}}/{{cookiecutter.package_name}}/cpp_{{cookiecutter.module_name}}/{{cookiecutter.module_name}}.cpp
et_micc/templates/module-cpp/{{cookiecutter.project_name}}/{{cookiecutter.package_name}}/cpp_{{cookiecutter.module_name}}/{{cookiecutter.module_name}}.rst
et_micc/templates/module-f90/{{cookiecutter.project_name}}/tests/test_f90_{{cookiecutter.module_name}}.{{cookiecutter.py}}
et_micc/templates/module-f90/{{cookiecutter.project_name}}/{{cookiecutter.package_name}}/f90_{{cookiecutter.module_name}}/CMakeLists.txt
et_micc/templates/module-f90/{{cookiecutter.project_name}}/{{cookiecutter.package_name}}/f90_{{cookiecutter.module_name}}/{{cookiecutter.module_name}}.f90
et_micc/templates/module-f90/{{cookiecutter.project_name}}/{{cookiecutter.package_name}}/f90_{{cookiecutter.module_name}}/{{cookiecutter.module_name}}.rst
et_micc/templates/module-py/{{cookiecutter.project_name}}/tests/test_{{cookiecutter.module_name}}.{{cookiecutter.py}}
et_micc-1.1.8.dist-info/entry_points.txt
et_micc-1.1.8.dist-info/LICENSE
et_micc-1.1.8.dist-info/WHEEL
et_micc-1.1.8.dist-info/METADATA
et_micc-1.1.8.dist-info/RECORD
