Metadata-Version: 2.1
Name: et-micc
Version: 1.1.8
Summary: A practical Python project skeleton generator.
Home-page: https://github.com/etijskens/et-micc
License: MIT
Keywords: project management
Author: Engelbert Tijskens
Author-email: engelbert.tijskens@uantwerpen.be
Requires-Python: >=3.6,<4.0
Classifier: License :: OSI Approved :: MIT License
Classifier: Programming Language :: Python :: 3
Classifier: Programming Language :: Python :: 3.6
Classifier: Programming Language :: Python :: 3.7
Classifier: Programming Language :: Python :: 3.8
Classifier: Programming Language :: Python :: 3.9
Requires-Dist: click (>=7.0,<8.0)
Requires-Dist: cookiecutter (>=1.6.0,<2.0.0)
Requires-Dist: pypi-simple (>=0.8.0,<0.9.0)
Requires-Dist: semantic_version (>=2.8.3,<3.0.0)
Requires-Dist: sphinx-click (>=2.3.0,<3.0.0)
Requires-Dist: sphinx-rtd-theme (>=0.4.3,<0.5.0)
Requires-Dist: tomlkit (>=0.5.8,<0.6.0)
Requires-Dist: walkdir (>=0.4.1,<0.5.0)
Project-URL: Repository, https://github.com/etijskens/et-micc
